[
{
     "image": "https://envs.sh/LzI.jpg",
     "name": "Asees 2018 Punjabi Language 480p" ,
     "link": "https://www.diskwala.com/app/67f52d6fafb9f70b32c3e85d"
},

{
     "image": "https://envs.sh/Lzn.jpg",
     "name": "Daana Paani 2018 Punjabi Language" ,
     "link": "https://www.diskwala.com/app/67f52daeafb9f70b32c3ec61"
},

{
     "image": "https://envs.sh/LzA.jpg",
     "name": "Nanak Naam Jahaz Hai 2024 Punjabi mkv" ,
     "link": "https://www.diskwala.com/app/67f52e17afb9f70b32c3eea6"
},
{
     "image": "https://envs.sh/LbC.jpg",
     "name": "Ikko Mikke (2020) Punjabi 480p HDRip x264 AAC ESubs mkv" ,
     "link": "https://www.diskwala.com/app/67ee2b95afb9f70b32aaabf8"
},
{
     "image": "https://envs.sh/Lb5.jpg",
     "name": "Sohreyan Da Pind Aa Gaya (2022) Punjabi" ,
     "link": "https://www.diskwala.com/app/67ee2b98afb9f70b32aaac05"
},
{
     "image": "https://envs.sh/LbP.jpg",
     "name": "Bahuroopyia (2025) Punjabi" ,
     "link": "https://www.diskwala.com/app/67ee2bb1afb9f70b32aaac47"
}     
]
